portablesource/Version.py
portablesource/__init__.py
portablesource/__main__.py
portablesource/config.py
portablesource/envs_manager.py
portablesource/get_gpu.py
portablesource/repository_installer.py
portablesource/utils.py
portablesource-0.1.2.post5.dist-info/METADATA
portablesource-0.1.2.post5.dist-info/WHEEL
portablesource-0.1.2.post5.dist-info/entry_points.txt
portablesource-0.1.2.post5.dist-info/licenses/LICENSE
portablesource-0.1.2.post5.dist-info/RECORD
