Metadata-Version: 2.4
Name: portablesource
Version: 0.1.2.post5
Summary: Library for portable source!
Project-URL: GitHub, https://github.com/portablesource/portablesource-cli
Project-URL: Changelog, https://github.com/portablesource/portablesource-cli/releases
Project-URL: Contact, https://t.me/NeuroDonu
Project-URL: Download, https://github.com/portablesource/portablesource-cli/releases
Project-URL: Homepage, https://github.com/portablesource/portablesource-cli
Author-email: NeuroDonu <admin@neurodonu.dev>
License-Expression: MIT
License-File: LICENSE
Requires-Python: >=3.8
Requires-Dist: requests
Requires-Dist: tqdm
